README.rst
setup.cfg
setup.py
stb_utils/__init__.py
stb_utils/address.py
stb_utils/conversions.py
stb_utils/currency.py
stb_utils/decorators.py
stb_utils/encoding.py
stb_utils/hexadecimal.py
stb_utils/types.py
stb_utils/typing/__init__.py
stb_utils/typing/misc.py
stb_utils_testnet.egg-info/PKG-INFO
stb_utils_testnet.egg-info/SOURCES.txt
stb_utils_testnet.egg-info/dependency_links.txt
stb_utils_testnet.egg-info/not-zip-safe
stb_utils_testnet.egg-info/requires.txt
stb_utils_testnet.egg-info/top_level.txt